{
  "title": "Trump - Escobilla de Inodoro + Soporte + Rollos de Papel higiénico Donald Trump Divertido Limpiador para la Limpieza Profunda del baño Haz Que tu Inodoro vuelva a ser Genial",
  "image": "https://m.media-amazon.com/images/I/51iQHu4jInL._AC_SL1000_.jpg",
  "asin": "B07VQS9GV8",
  "reviews": [
    {
      "title": "Cheer  the bathroom  up",
      "name": "John roberts",
      "date": "2021-02-17T23:00:00.000Z",
      "country": "Reino Unido",
      "stars": 4
    },
    {
      "title": "Bestes Geschenk ever!",
      "name": "Ariane",
      "date": "2021-02-04T23:00:00.000Z",
      "country": "Alemania",
      "stars": 5
    },
    {
      "title": "très intéressant",
      "name": "zhang",
      "date": "2020-11-19T23:00:00.000Z",
      "country": "Francia",
      "stars": 5
    },
    {
      "title": "Keine ahnung",
      "name": "Gailgodd",
      "date": "2021-01-21T23:00:00.000Z",
      "country": "Alemania",
      "stars": 5
    },
    {
      "title": "Lustig",
      "name": "Dieter Thelen",
      "date": "2020-01-29T23:00:00.000Z",
      "country": "Alemania",
      "stars": 4
    },
    {
      "title": "Deko",
      "name": "Karen Brammeyer",
      "date": "2020-12-18T23:00:00.000Z",
      "country": "Alemania",
      "stars": 5
    },
    {
      "title": "Lustiges Geschenk",
      "name": "Linda",
      "date": "2019-12-19T23:00:00.000Z",
      "country": "Alemania",
      "stars": 5
    },
    {
      "title": "unterirdisch",
      "name": "Ria Schlotmann",
      "date": "2020-08-08T22:00:00.000Z",
      "country": "Alemania",
      "stars": 1
    },
    {
      "title": "So ergibt Trump wenigstens einen Sinn",
      "name": "Der letzte Lude",
      "date": "2020-02-06T23:00:00.000Z",
      "country": "Alemania",
      "stars": 5
    }
  ]
}